quart_db-0.12.0.dist-info/METADATA
quart_db-0.12.0.dist-info/WHEEL
quart_db-0.12.0.dist-info/entry_points.txt
quart_db-0.12.0.dist-info/licenses/LICENSE
quart_db/__init__.py
quart_db/_migration.py
quart_db/backends/__init__.py
quart_db/backends/aiosqlite.py
quart_db/backends/asyncpg.py
quart_db/backends/psycopg.py
quart_db/extension.py
quart_db/interfaces.py
quart_db/py.typed
quart_db-0.12.0.dist-info/RECORD
