Metadata-Version: 2.1
Name: quart-db
Version: 0.12.0
Summary: Quart-DB is a Quart extension that provides managed connection(s) to database(s).
Author-Email: pgjones <philip.graham.jones@googlemail.com>
License: MIT
Classifier: Development Status :: 3 - Alpha
Classifier: Environment :: Web Environment
Classifier: Intended Audience :: Developers
Classifier: License :: OSI Approved :: MIT License
Classifier: Operating System :: OS Independent
Classifier: Programming Language :: Python
Classifier: Programming Language :: Python :: 3
Classifier: Programming Language :: Python :: 3.10
Classifier: Programming Language :: Python :: 3.11
Classifier: Programming Language :: Python :: 3.12
Classifier: Programming Language :: Python :: 3.13
Classifier: Programming Language :: Python :: 3.14
Classifier: Topic :: Internet :: WWW/HTTP :: Dynamic Content
Classifier: Topic :: Software Development :: Libraries :: Python Modules
Requires-Python: >=3.10
Requires-Dist: asyncpg>=0.25.0
Requires-Dist: buildpg>=0.4
Requires-Dist: quart>=0.16.3
Requires-Dist: typing_extensions; python_version < "3.13"
Provides-Extra: docs
Requires-Dist: pydata_sphinx_theme; extra == "docs"
Provides-Extra: erdiagram
Requires-Dist: eralchemy; extra == "erdiagram"
Provides-Extra: psycopg
Requires-Dist: psycopg>=3.2; extra == "psycopg"
Provides-Extra: sqlite
Requires-Dist: aiosqlite; extra == "sqlite"
